{
  "diversions": [
    {
      "id": 36640,
      "number": "V2602-006",
      "title": "Přerušení provozu linky 62",
      "latitude": 49.182042,
      "longitude": 16.588057,
      "validFrom": "2026-02-23T05:00:00+01:00",
      "validTo": "2026-07-23T20:00:00+02:00",
      "isValid": false,
      "publicTextHtml": "<p>Z důvodu stavebních prací nebude <strong>od pondělí 23. února 2026 do ukončení prací</strong> (předpoklad do 27. července 2026) pro veškerou dopravu průjezdná část ulice Vinohrady.</p>\n\n<p> </p>\n\n<drupal-media data-align=\"left\" data-entity-type=\"media\" data-entity-uuid=\"91942a3b-47db-456f-b278-54ed4d56192f\" data-view-mode=\"\"></drupal-media>\n\n<p><strong> Autobusová linka 62</strong> bude po dobu trvání stavebních prací mimo provoz.<br />\n• Zastávku <strong>Červený kopec</strong> nebude možné obsloužit.<br />\n• V úseku Mendlovo náměstí – Nemocnice Milosrdných bratří bude možné využít pravidelné tramvajové linky.</p>\n",
      "privateTextHtml": null,
      "type": "V",
      "affectedLines": [
        "62"
      ]
    },
    {
      "id": 41,
      "number": "VP 2602-019",
      "title": "žel. trať. Brno-Horní Heršpice - Střelice jedna kolej",
      "latitude": 49.162456,
      "longitude": 16.586931,
      "validFrom": "2026-02-21T08:20:00+01:00",
      "validTo": "2026-03-01T16:35:00+01:00",
      "isValid": false,
      "publicTextHtml": "Některé vlaky\u00A0linky<font color=\"#800000\"><strong> S4</strong></font>\u00A0pojedou v odchylných časových polohách dle\u00A0výlukového jízdního řádu linky<font color=\"#800000\"><strong> S4</strong></font>.\u00A0(Z Brna hl.n. dříve, ze Střelic do Brna později.). Po dobu výluky budou\u00A0z Brna hl.n. do Střelic a zpět\u00A0nahrazeny vlaky\u00A0linky<font color=\"#800000\"><strong> S41</strong></font>\u00A0náhradní autobusovou dopravou (NAD), která bude organizována podle\u00A0výlukového jízdního řádu linky xS41. ",
      "privateTextHtml": null,
      "type": "V",
      "affectedLines": [
        "S4",
        "S41",
        "xS41"
      ]
    },
    {
      "id": 38,
      "number": "VP 2602-018",
      "title": "žel. trať v úseku Veselí nad Moravou – Strážnice",
      "latitude": 48.921514,
      "longitude": 17.334406,
      "validFrom": "2026-02-19T08:00:00+01:00",
      "validTo": "2026-02-20T14:05:00+01:00",
      "isValid": true,
      "publicTextHtml": "Vlaky\u00A0linky<font color=\"#800000\"><strong> S91</strong></font>\u00A0budou v úseku Strážnice – Veselí nad Moravou po dobu výluky\u00A0nahrazeny náhradní autobusovou dopravou (NAD)\u00A0jedoucí podle výlukového\u00A0jízdního řádu jako\u00A0linka xS91.. ",
      "privateTextHtml": null,
      "type": "V",
      "affectedLines": [
        "S91",
        "xS91"
      ]
    },
    {
      "id": 36699,
      "number": "",
      "title": "Provoz MHD o jarních prázdninách",
      "latitude": 49.191943,
      "longitude": 16.612111,
      "validFrom": "2026-02-16T00:00:00+01:00",
      "validTo": "2026-02-20T23:59:59+01:00",
      "isValid": true,
      "publicTextHtml": "<p><strong>Ve dnech </strong><strong>16. – 20. února 2026</strong> (jarní prázdniny) pojedou linky 1–84 podle jízdních řádů pro <strong>pracovní dny – prázdniny</strong>.</p>\n\n<p>• Autobusové linky 66, š85, š86 a š88 budou mimo provoz.</p>\n\n<p> </p>\n\n<drupal-media data-align=\"left\" data-entity-type=\"media\" data-entity-uuid=\"e4b7c0ba-8762-481e-9ccd-098e280c4d65\" data-view-mode=\"\"></drupal-media>\n\n<p> U spojů regionálních linek doporučujeme věnovat pozornost poznámkám v jízdních řádech.</p>\n",
      "privateTextHtml": null,
      "type": "D",
      "affectedLines": [
        "1",
        "2",
        "3",
        "4",
        "5",
        "6",
        "7",
        "8",
        "9",
        "10",
        "12",
        "25",
        "26",
        "27",
        "30",
        "31",
        "32",
        "33",
        "34",
        "35",
        "36",
        "37",
        "38",
        "39",
        "40",
        "41",
        "x41",
        "42",
        "44",
        "46",
        "47",
        "49",
        "50",
        "E50",
        "52",
        "54",
        "55",
        "E56",
        "57",
        "58",
        "62",
        "64",
        "65",
        "66",
        "67",
        "68",
        "69",
        "70",
        "72",
        "75",
        "E75",
        "x75",
        "E76",
        "77",
        "78",
        "84",
        "š85",
        "š86",
        "š88"
      ]
    },
    {
      "id": 40,
      "number": "PO 2602-005",
      "title": "zast. Šumná, žel. st. - bez obsluhy bus linkou 830",
      "latitude": 48.922926,
      "longitude": 15.873887,
      "validFrom": "2026-02-09T00:00:00+01:00",
      "validTo": "2026-05-08T23:59:00+02:00",
      "isValid": true,
      "publicTextHtml": "Linka<font color=\"#009240\"><strong> 830</strong></font>\u00A0- veškeré spoje v obou směrech nebudou až do odvolání obsluhovat zastávku Šumná, žel. st. Otáčet se budou v obci Šumná u obecního úřadu. ",
      "privateTextHtml": null,
      "type": "V",
      "affectedLines": [
        "830"
      ]
    },
    {
      "id": 22,
      "number": "PO 2602-003",
      "title": "Dobšice, silnice II/412, most ev.č. 412-004",
      "latitude": 48.851444,
      "longitude": 16.089692,
      "validFrom": "2026-02-02T00:00:00+01:00",
      "validTo": "2026-10-31T23:59:00+01:00",
      "isValid": true,
      "publicTextHtml": "Linka<font color=\"#009240\"><strong> 108</strong></font>\u00A0- jede odklonovou trasou mezi okružní křižovatkou silnic I/53 x II/408 až zastávkou Znojmo, aut. nádr. v trase buď přes Suchohrdly u Znojma nebo přes ul. Vídeňskou ve Znojmě.<br/><br/> Linka<font color=\"#009240\"><strong> 822</strong></font>\u00A0-\u00A0 jede odklonovou trasou mezi okružní křižovatkou silnic I/53 x II/408 až zastávkou Znojmo, Suchohrdelská, hřbitov v trase buď přes Suchohrdly u Znojma nebo přes Dobšice, ul. Znojemskou, bez vynechání zastávek. ",
      "privateTextHtml": null,
      "type": "V",
      "affectedLines": [
        "108",
        "822"
      ]
    },
    {
      "id": 19,
      "number": "VP 2601-202",
      "title": "Drnovice u Lysic, most 3674-2",
      "latitude": 49.469527,
      "longitude": 16.543865,
      "validFrom": "2026-01-26T00:00:00+01:00",
      "validTo": "2026-09-05T23:59:00+02:00",
      "isValid": true,
      "publicTextHtml": "Z důvodu opravy mostu v obci Drnovice bude zcela vyloučen provoz autobusů v úseku Voděrady, náměstí - Drnovice. Autobusová linka<font color=\"#009240\"><strong> 257</strong></font> pojede v úseku Voděrady, náměstí - Lysice, pohostinství\u00A0obousměrným odklonem\u00A0přes zastávky Krhov, Pohodlí a Lysice, výzkum.\u00A0Vynechá zastávky Voděrady, horní zastávka, Drnovice, Drnovice, horní zastávka a Lysice, škola. Obsluha zastávky Lysice, škola točna\u00A0bude zajištěna linkou<font color=\"#009240\"><strong> 257</strong></font> pouze při jízdě ve směru Lysice - Kozárov / Olešnice. Na linku<font color=\"#009240\"><strong> 257</strong></font> bude v exponovaných časech v PRACOVNÍ DNY navazovat linka<font color=\"#009240\"><strong> 245</strong></font> v zastávce Lysice, pohostinství směr do / z Drnovic. Náhradní dopravu zajistí výlukové spoje linky<font color=\"#009240\"><strong> 245</strong></font> v úseku Lysice, pohostinství - Drnovice a pravidelné spoje linky<font color=\"#009240\"><strong> 301</strong></font> do zastávek Drnovice, rozcestí 0,5 a Drnovice, rozcestí Kunice. . . ",
      "privateTextHtml": null,
      "type": "V",
      "affectedLines": [
        "245",
        "257"
      ]
    },
    {
      "id": 36202,
      "number": "",
      "title": "Dočasné přeložení zastávky Za Lužánkami",
      "latitude": 49.209511,
      "longitude": 16.609503,
      "validFrom": "2026-01-17T14:00:00+01:00",
      "validTo": "2026-08-31T23:59:59+02:00",
      "isValid": true,
      "publicTextHtml": "<p><strong class=\"red\">AKTUALIZACE:</strong> <strong>Od 8:00 hod. v úterý 17. února 2026</strong> je přeložena také zastávka <strong>Za Lužánkami </strong>pro linku 67 směr Jundrov přibližně o 140 metrů vzad před křižovatku s ulicí Erbenovou.</p>\n\n<p>Z důvodu stavebních prací je <strong>od 14:00 hod. v sobotu 17. ledna 2026 do ukončení prací</strong> (předpoklad do 31. srpna 2026) přeložena zastávka <strong>Za Lužánkami</strong>:<br />\n• Pro <strong>linku 67</strong> směr Avion Shopping Park přibližně o 140 metrů vzad do ulice Sportovní před výjezd z parkoviště.<br />\n• Pro <strong>linky 25</strong> a <strong>26</strong> směr Jírova / Štefánikova čtvrť ke středovému ostrůvku přibližně v úrovni stávající zastávky.</p>\n",
      "privateTextHtml": null,
      "type": "Z",
      "affectedLines": [
        "25",
        "26",
        "67"
      ]
    },
    {
      "id": 12,
      "number": "2601 Mokrá-Horákov, Horákov",
      "title": "Mokrá-Horákov, Horákov",
      "latitude": 49.215663,
      "longitude": 16.749580,
      "validFrom": "2026-01-01T00:00:00+01:00",
      "validTo": "2026-04-30T23:59:00+02:00",
      "isValid": true,
      "publicTextHtml": "Zastávka Mokrá-Horákov, Horákov je pro oba směry přesunuta do prostoru obratiště autobusů. ",
      "privateTextHtml": null,
      "type": "V",
      "affectedLines": [
        "701"
      ]
    },
    {
      "id": 35684,
      "number": "V2506-044",
      "title": "Dočasné zrušení obsluhy zastávky Uzbecká",
      "latitude": 49.172343,
      "longitude": 16.583318,
      "validFrom": "2025-12-19T23:00:00+01:00",
      "validTo": "2026-05-20T23:59:59+02:00",
      "isValid": true,
      "publicTextHtml": "<drupal-media data-align=\"left\" data-entity-type=\"media\" data-entity-uuid=\"b2d6d691-c35d-4b6e-be2d-98f2754298c0\" data-view-mode=\"\"></drupal-media>\n\n<p> Z důvodu stavebních prací nebude <strong>od 23:00 hod. 19. prosince 2025</strong> do ukončení prací (předpoklad do poloviny května 2026) možné obsloužit zastávku <strong>Uzbecká </strong>linek 40 a N90 směr Nemocnice Bohunice.</p>\n",
      "privateTextHtml": null,
      "type": "V",
      "affectedLines": [
        "40",
        "N90"
      ]
    },
    {
      "id": 11,
      "number": "PO 2512-245",
      "title": "Znojmo, ul. Vančurova",
      "latitude": 48.866454,
      "longitude": 16.045210,
      "validFrom": "2025-12-17T00:00:00+01:00",
      "validTo": "2026-05-31T23:59:00+02:00",
      "isValid": true,
      "publicTextHtml": "Linka<font color=\"#2C89C8\"><strong> 802</strong></font>\u00A0vynechá závlek k zastávce Vančurova DPS.<br/><br/> Linka<font color=\"#009240\"><strong> 806</strong></font>\u00A0pojede po své trase, zastávku Vančurova DPS obslouží v přeložené poloze. ",
      "privateTextHtml": null,
      "type": "V",
      "affectedLines": [
        "802",
        "806"
      ]
    },
    {
      "id": 34971,
      "number": "V2511-136",
      "title": "Omezení provozu autobusů v České a Lelekovicích",
      "latitude": 49.281825166667,
      "longitude": 16.565033166667,
      "validFrom": "2025-11-24T04:00:00+01:00",
      "validTo": null,
      "isValid": true,
      "publicTextHtml": "<p><span><span>Z důvodu havarijního stavu mostu přes železniční trať bude <strong>od 4:00 hod. v pondělí 24. listopadu 2025 do odvolání</strong> omezen provoz mezi Českou a Lelekovicemi. </span></span></p>\n\n<p> </p>\n\n<drupal-media data-align=\"left\" data-entity-type=\"media\" data-entity-uuid=\"91942a3b-47db-456f-b278-54ed4d56192f\" data-view-mode=\"\"></drupal-media>\n\n<p><span><span><strong> Autobusová linka 41</strong> bude v provozu pouze v úseku <strong>Královo Pole, nádraží – Mácova (– Ivanovice, Globus)</strong>.</span></span></p>\n\n<p> </p>\n\n<drupal-media data-align=\"left\" data-entity-type=\"media\" data-entity-uuid=\"fc4dd07b-c8f7-46d9-9dbc-626086b3714a\" data-view-mode=\"\"></drupal-media>\n\n<p><span><span> Náhradní dopravu v denní době zajistí <strong>autobusová linka x41</strong> v trase <strong>(Ivanovice, Globus –) Mácova – Lelekovice (– Vranov)</strong>.<br />\n• Spoje jedoucí <strong>na Mácovu</strong> a <strong>z Globusu</strong> obslouží v Ivanovicích zastávky v pořadí (<strong>Česká, Nádavky</strong> ») <strong>Příjezdová </strong>» <strong>Kouty </strong>» <strong>Mácova</strong>, spoje jedoucí do Globusu v pořadí (<strong>Česká, Nádavky</strong> ») <strong>Mácova</strong> » <strong>Kouty</strong> » <strong>Příjezdová</strong>.<br />\n• Mimo dobu ranní a odpolední špičky budou spoje vedené do Vranova ukončeny již v zastávce <strong>Vranov, smyčka</strong>, nebudou tak obslouženy zastávky <strong>Vranov, křižovatka </strong>a <strong>Vranov, myslivna</strong>.</span></span></p>\n\n<p> </p>\n\n<drupal-media data-align=\"left\" data-entity-type=\"media\" data-entity-uuid=\"91942a3b-47db-456f-b278-54ed4d56192f\" data-view-mode=\"\"></drupal-media>\n\n<p><span><span> Spoje <strong>noční autobusové linky N91</strong> pravidelně vedené z / do Lelekovic pojedou pouze v úseku <strong>Labská – Mácova</strong> a poté odklonem do zastávky <strong>Ivanovice, Globus</strong>.</span></span></p>\n\n<p> </p>\n\n<drupal-media data-align=\"left\" data-entity-type=\"media\" data-entity-uuid=\"fc4dd07b-c8f7-46d9-9dbc-626086b3714a\" data-view-mode=\"\"></drupal-media>\n\n<p><span><span> Náhradní doprava v nočních hodinách bude zajištěna autobusovou linkou x91 v trase <strong>Mácova – Lelekovice, u kříže</strong>.</span></span></p>\n\n<p> </p>\n\n<drupal-media data-align=\"left\" data-entity-type=\"media\" data-entity-uuid=\"e4b7c0ba-8762-481e-9ccd-098e280c4d65\" data-view-mode=\"\"></drupal-media>\n\n<p><span><span> Linky 41 a N91 budou Ivanovice obsluhovat <strong>pouze proti směru hodinových ručiček</strong>, v obou směrech a všech variantách trasy obslouží postupně zastávky <strong>Mácova</strong> » <strong>Kouty</strong> » <strong>Příjezdová </strong>směr město<strong>.</strong></span></span></p>\n\n<p> </p>\n\n<drupal-media data-align=\"left\" data-entity-type=\"media\" data-entity-uuid=\"e4b7c0ba-8762-481e-9ccd-098e280c4d65\" data-view-mode=\"\"></drupal-media>\n\n<p><span><span><strong> Linka x41 </strong>bude s výjimkou spojů <strong>do Globusu </strong>Ivanovice obsluhovat <strong>po směru hodinových ručiček </strong>a obslouží postupně zastávky <strong>Příjezdová </strong>» <strong>Kouty </strong>» <strong>Mácova </strong>směr Lelekovice.</span></span></p>\n\n<p> </p>\n\n<drupal-media data-align=\"left\" data-entity-type=\"media\" data-entity-uuid=\"e4b7c0ba-8762-481e-9ccd-098e280c4d65\" data-view-mode=\"\"></drupal-media>\n\n<p><span><span> Vzájemný přestup mezi linkami 41 a x41, resp. N91 a x91 bude umožněn v zastávce <strong>Mácova</strong>.</span></span></p>\n\n<p> </p>\n\n<p> </p>\n\n<drupal-media data-align=\"left\" data-entity-type=\"media\" data-entity-uuid=\"081d77d8-0e25-42e5-805f-a4a5b5daf1ca\" data-view-mode=\"\"></drupal-media>\n\n<p><em> Schéma dopravních opatření – <a href=\"https://dpmb.cz/sites/default/files/infotabule/info_v2511-136_web.pdf\" target=\"_blank\">ke stažení</a></em></p>\n\n<drupal-media data-align=\"left\" data-entity-type=\"media\" data-entity-uuid=\"081d77d8-0e25-42e5-805f-a4a5b5daf1ca\" data-view-mode=\"\"></drupal-media>\n\n<p><em> Jízdní řády dotčených linek budou k dispozici v sekci <a href=\"https://www.dpmb.cz/jizdni-rady-zastavek-linek\">Jízdní řády</a>.</em></p>\n",
      "privateTextHtml": null,
      "type": "V",
      "affectedLines": [
        "41",
        "x41",
        "N91",
        "x91"
      ]
    },
    {
      "id": 34527,
      "number": "V2511-123",
      "title": "Uzavírka ulice Fryčajovy",
      "latitude": 49.232484,
      "longitude": 16.64875,
      "validFrom": "2025-11-01T06:15:00+01:00",
      "validTo": null,
      "isValid": true,
      "publicTextHtml": "<p>Z důvodu rekonstrukce inženýrských sítí a povrchu komunikace je <strong>od 6:15 hod. v sobotu 1. listopadu 2025</strong> <strong>do ukončení prací</strong> (předpoklad minimálně do jara 2027) pro veškerou dopravu uzavřena ulice Fryčajova v Obřanech.</p>\n\n<p> </p>\n\n<drupal-media data-align=\"left\" data-entity-type=\"media\" data-entity-uuid=\"96a7086f-5aad-4568-932f-78e7c0655fd1\" data-view-mode=\"\"></drupal-media>\n\n<p> Všechny spoje <strong>tramvajové linky 4</strong> jsou vedeny až do zastávky <strong>Obřany, Babická</strong>.<br />\n• Ruší se tak ukončení vybraných spojů v zastávce <strong>Maloměřický most</strong>.</p>\n\n<p> </p>\n\n<drupal-media data-align=\"left\" data-entity-type=\"media\" data-entity-uuid=\"91942a3b-47db-456f-b278-54ed4d56192f\" data-view-mode=\"\"></drupal-media>\n\n<p><strong> Autobusová linka 57</strong> je v provozu pouze v úseku (<strong>Vranov, smyčka –) Haškova – Maloměřický most</strong>.<br />\n• Ruší se tak ukončení vybraných spojů v zastávce <strong>Obřany, sídliště</strong> v ranních hodinách.</p>\n\n<p> </p>\n\n<drupal-media data-align=\"left\" data-entity-type=\"media\" data-entity-uuid=\"91942a3b-47db-456f-b278-54ed4d56192f\" data-view-mode=\"\"></drupal-media>\n\n<p><strong> Autobusová linka 75</strong> je v provozu pouze v úseku <strong>(Slatina, nádraží –) Vozovna Slatina – Tomkovo náměstí</strong>.<br />\n• Ve směru ze Slatiny jede ze zastávky <strong>Židenice, kasárna</strong> přes zastávky <strong>Karlova </strong>a <strong>Maloměřický most</strong> do zastávky <strong>Tomkovo náměstí</strong>.<br />\n• Ve směru do Slatiny jede z <strong>Tomkova náměstí</strong> (obsluhuje jak zastávku za ústím ulice Valchařské, tak zastávku linky 84) přímo do zastávky <strong>Židenice, kasárna</strong> a dále po běžné trase.<br />\n• Mezi Maloměřicemi, Obřany a Bílovicemi nad Svitavou je náhradou možné využít linky 4 a x75.</p>\n\n<p> </p>\n\n<drupal-media data-align=\"left\" data-entity-type=\"media\" data-entity-uuid=\"fc4dd07b-c8f7-46d9-9dbc-626086b3714a\" data-view-mode=\"\"></drupal-media>\n\n<p> Náhradní dopravu zajišťuje mimořádná <strong>minibusová linka x75</strong> v trase <strong>Obřanský most – Hradiska – Obřany, sídliště (– Bílovice nad Svitavou, železniční stanice)</strong>.<br />\n• Zastávka <strong>Hradiska </strong>je v obou směrech zřízena v horní části stejnojmenné komunikace.<br />\n• V úseku Obřany, sídliště – Bílovice nad Svitavou, železniční stanice jede po trase a zastávkách linky 75.</p>\n\n<p> </p>\n\n<drupal-media data-align=\"left\" data-entity-type=\"media\" data-entity-uuid=\"91942a3b-47db-456f-b278-54ed4d56192f\" data-view-mode=\"\"></drupal-media>\n\n<p><strong> Noční autobusová linka N94</strong> je ukončena v zastávce <strong>Obřany, Babická</strong>.<br />\n• Ruší se tak provoz vybraných spojů až do Bílovic nad Svitavou.</p>\n\n<p> </p>\n\n<drupal-media data-align=\"left\" data-entity-type=\"media\" data-entity-uuid=\"b2d6d691-c35d-4b6e-be2d-98f2754298c0\" data-view-mode=\"\"></drupal-media>\n\n<p> Zastávky <strong>Hlaváčova </strong>a <strong>Bílovická </strong>jsou po dobu výluky zcela bez obsluhy.</p>\n\n<p> </p>\n\n<drupal-media data-align=\"left\" data-entity-type=\"media\" data-entity-uuid=\"e4b7c0ba-8762-481e-9ccd-098e280c4d65\" data-view-mode=\"\"></drupal-media>\n\n<p> S ohledem na omezenou kapacitu minibusové linky x75 a výrazně delší dobu jízdy doporučujeme pro cesty mezi Brnem a Bílovicemi nad Svitavou primárně využívat <strong>železniční linku S2</strong> s přestupem na autobusové linky x75 a 211 v zastávce <strong>Bílovice nad Svitavou, železniční stanice</strong>.</p>\n\n<p> </p>\n\n<drupal-media data-align=\"left\" data-entity-type=\"media\" data-entity-uuid=\"e4b7c0ba-8762-481e-9ccd-098e280c4d65\" data-view-mode=\"\"></drupal-media>\n\n<p> V průběhu uzavírky může v rámci dílčích etap stavebních prací docházet k drobným změnám zavedených opatření.</p>\n\n<p> </p>\n\n<p><strong class=\"red\"><span><span><span>AKTUALIZACE 26. listopadu 2025: Od noci z pátku 28. listopadu na sobotu 29. listopadu 2025 je zahájen provoz výlukové noční midibusové linky x94. </span></span></span></strong></p>\n\n<drupal-media data-align=\"left\" data-entity-type=\"media\" data-entity-uuid=\"fc4dd07b-c8f7-46d9-9dbc-626086b3714a\" data-view-mode=\"\"></drupal-media>\n\n<p><strong> Noční autobusová linka</strong><span><span><span> <strong>x94</strong> jede po trase <strong>Brno, Tomkovo náměstí </strong>(návaznost s linkou N94) <strong>– Ochoz u Brna – Kanice – Řícmanice – Bílovice nad Svitavou – Brno, Obřany, sídliště</strong>.<br />\n• Ze zastávky <strong>Obřany, sídliště </strong>směr Brno spoje odjíždějí od označníku směr Bílovice nad Svitavou.<br />\n• V Bílovicích nad Svitavou spoje zastavují oproti lince x75 na protisměrných zastávkách.<br />\n• V zastávkách <strong>Ochoz u Brna</strong>, <strong>Kanice</strong> a <strong>Řícmanice </strong>zastavují pouze spoje určené jízdním řádem, ostatní spoje jedou v úseku <strong>Brno, Tomkovo náměstí – Bílovice nad Svitavou, UP závody</strong> bez zastavení.</span></span></span></p>\n\n<p> </p>\n\n<drupal-media data-align=\"left\" data-entity-type=\"media\" data-entity-uuid=\"e4b7c0ba-8762-481e-9ccd-098e280c4d65\" data-view-mode=\"\"></drupal-media>\n\n<p><span><span><span> Linka x94 zároveň nahrazuje vybrané spoje linky x75 v okrajových denních dobách.</span></span></span></p>\n\n<p> </p>\n\n<drupal-media data-align=\"left\" data-entity-type=\"media\" data-entity-uuid=\"e4b7c0ba-8762-481e-9ccd-098e280c4d65\" data-view-mode=\"\"></drupal-media>\n\n<p><span><span><span> Tarifní opatření:<br />\n• Při jízdě linkou x94 mezi zastávkami v tarifní zóně 100 držitelé příslušné předplatní jízdenky nehradí jízdné za zóny 210 a 215, postačuje předplatní jízdenka pro zónu 100.<br />\n• Při jízdě linkou x94 mezi tarifními zónami 100 a 215 držitelé příslušné předplatní jízdenky nehradí jízdné za zónu 210, postačuje předplatní jízdenka pro zóny 100 a 215.<br />\n• Cestující s jednorázovou jízdenkou hradí jízdné podle skutečně projetých tarifních zón.<br />\n• Na lince probíhá mimo zastávky Tomkovo náměstí a Obřany, sídliště <strong>nástup cestujících výhradně předními dveřmi </strong>s kontrolou nebo prodejem jízdních dokladů řidičem.</span></span></span></p>\n\n<p> </p>\n\n<drupal-media data-align=\"left\" data-entity-type=\"media\" data-entity-uuid=\"081d77d8-0e25-42e5-805f-a4a5b5daf1ca\" data-view-mode=\"\"></drupal-media>\n\n<p><em> Schéma dopravních opatření – <a href=\"https://dpmb.cz/sites/default/files/infotabule/info_v2511-123_web.pdf\" target=\"_blank\">ke stažení</a></em></p>\n\n<drupal-media data-align=\"left\" data-entity-type=\"media\" data-entity-uuid=\"081d77d8-0e25-42e5-805f-a4a5b5daf1ca\" data-view-mode=\"\"></drupal-media>\n\n<p><em> Jízdní řády dotčených linek budou k dispozici v sekci <a href=\"https://www.dpmb.cz/jizdni-rady-zastavek-linek\">Jízdní řády</a>.</em></p>\n",
      "privateTextHtml": null,
      "type": "V",
      "affectedLines": [
        "4",
        "57",
        "75",
        "x75",
        "N94",
        "x94",
        "211"
      ]
    },
    {
      "id": 34144,
      "number": "V2510-112",
      "title": "Omezení provozu tramvají ve smyčce Ečerova",
      "latitude": 49.218286,
      "longitude": 16.508994,
      "validFrom": "2025-10-18T00:00:00+02:00",
      "validTo": "2026-08-31T23:30:00+02:00",
      "isValid": true,
      "publicTextHtml": "<p>Z důvodu stavebních úprav ve smyčce Ečerova v souvislosti se stavbou nové tramvajové trati na sídliště Kamechy došlo <strong>od soboty 18. října 2025</strong> <strong>do ukončení prací</strong> (předpoklad do konce srpna 2026) ke změně organizace provozu tramvajových linek v Bystrci.</p>\n\n<p> </p>\n\n<drupal-media data-align=\"left\" data-entity-type=\"media\" data-entity-uuid=\"bc4c9a93-c8e0-447b-9750-d0ec753169bf\" data-view-mode=\"\"></drupal-media>\n\n<p><strong> Tramvajová linka 1</strong> je v provozu v úseku <strong>Řečkovice – Přístaviště</strong> a poté je odkloněna do smyčky <strong>Rakovecká</strong>.<br />\n• Neobsluhuje tak zastávky <strong>Kubíčkova</strong>, <strong>Ondrouškova </strong>a <strong>Ečerova</strong>.</p>\n\n<p> </p>\n\n<drupal-media data-align=\"left\" data-entity-type=\"media\" data-entity-uuid=\"96a7086f-5aad-4568-932f-78e7c0655fd1\" data-view-mode=\"\"></drupal-media>\n\n<p> Náhradou je do zastávky Ečerova prodloužena <strong>tramvajová linka 3</strong>.<br />\n• Neobsluhuje tak smyčku <strong>Rakovecká</strong>.<br />\n• Na prodloužené trase obsluhuje nácestné zastávky <strong>Kubíčkova </strong>a <strong>Ondrouškova</strong>.<br />\n• Zastávku <strong>Ečerova </strong>obsluhuje pro výstup i nástup v prostoru stávající výstupní zastávky.</p>\n\n<p> </p>\n\n<drupal-media data-align=\"left\" data-entity-type=\"media\" data-entity-uuid=\"e4b7c0ba-8762-481e-9ccd-098e280c4d65\" data-view-mode=\"\"></drupal-media>\n\n<p> Ostatní linky v oblasti zůstávají beze změny.</p>\n\n<p> </p>\n\n<drupal-media data-align=\"left\" data-entity-type=\"media\" data-entity-uuid=\"e4b7c0ba-8762-481e-9ccd-098e280c4d65\" data-view-mode=\"\"></drupal-media>\n\n<p> Pro cestování z centra města do západní části Bystrce a na sídliště Kamechy linkou 1 ve večerních hodinách doporučujeme využít přestup na autobusové linky 52 a 54 v terminálu Zoologická zahrada.</p>\n\n<p> </p>\n\n<drupal-media data-align=\"left\" data-entity-type=\"media\" data-entity-uuid=\"e4b7c0ba-8762-481e-9ccd-098e280c4d65\" data-view-mode=\"\"></drupal-media>\n\n<p> <em>Od soboty 18. října 2025 došlo k úpravě jízdních řádů na tramvajových linkách, které jsou k dispozici v sekci <a href=\"https://www.dpmb.cz/jizdni-rady-zastavek-linek\">Jízdní řády</a>.</em></p>\n\n<p> </p>\n\n<drupal-media data-align=\"left\" data-entity-type=\"media\" data-entity-uuid=\"081d77d8-0e25-42e5-805f-a4a5b5daf1ca\" data-view-mode=\"\"></drupal-media>\n\n<p><em> Schéma dopravních opatření – <a href=\"https://dpmb.cz/sites/default/files/infotabule/info_v2511-112_web.pdf\" target=\"_blank\">ke stažení</a></em></p>\n",
      "privateTextHtml": null,
      "type": "V",
      "affectedLines": [
        "1",
        "3"
      ]
    },
    {
      "id": 9,
      "number": "VP 2509-263",
      "title": "Znojmo, Nám. Svobody ",
      "latitude": 48.859125,
      "longitude": 16.048086,
      "validFrom": "2025-09-30T00:00:00+02:00",
      "validTo": "2026-07-31T23:59:00+02:00",
      "isValid": true,
      "publicTextHtml": "Linky<font color=\"#009240\"><strong> 806</strong></font> a <font color=\"#009240\"><strong>807</strong></font>\u00A0jedou od zastávky Pražská, Kolonka do zastávky Nám. Komenského odklonem přes zastávku Nám. Svobody, lázně. Vynechávají zastávky Nám. Svobody, horní brána a Horní náměstí. V opačném směru jedou přes zastávky Náměstí Komenského a Náměstí Svobody, lázně.. ",
      "privateTextHtml": null,
      "type": "V",
      "affectedLines": [
        "806",
        "807"
      ]
    },
    {
      "id": 8,
      "number": "PO 2509-172",
      "title": "Lanžhot, ulice náměstí a autobusové nádraží",
      "latitude": 48.724845,
      "longitude": 16.966717,
      "validFrom": "2025-09-10T00:00:00+02:00",
      "validTo": "2026-09-30T23:59:00+02:00",
      "isValid": true,
      "publicTextHtml": "Zastávky\u00A0Lanžhot, aut. nádr. budou přesunuty na hlavní silnici Břeclav - Lanžhot - Slovensko na ulici Masarykova\u00A0zhruba doprostřed mezi křiž. s\u00A0ulicemi Souhrady/Smetanova a Havlíčkova/Náměstí.. ",
      "privateTextHtml": null,
      "type": "V",
      "affectedLines": [
        "572"
      ]
    },
    {
      "id": 7,
      "number": "VP 2507-240",
      "title": "II/395 Dolní Kounice - Moravské Bránice",
      "latitude": 49.074316,
      "longitude": 16.447864,
      "validFrom": "2025-07-28T00:00:00+02:00",
      "validTo": "2026-05-31T23:59:00+02:00",
      "isValid": true,
      "publicTextHtml": "Linka<font color=\"#009240\"><strong> 154</strong></font>\u00A0pojede mezi zastávkami Dolní Kounice, Masarykovo nám. a Moravské Bránice, škola všemi spoji přes Nové Bránice. Zastávky na ulici Ivančické jsou bez obsluhy. ",
      "privateTextHtml": null,
      "type": "V",
      "affectedLines": [
        "154"
      ]
    },
    {
      "id": 31693,
      "number": "V2506-044",
      "title": "Omezení provozu v ulici Jihlavské – I. etapa",
      "latitude": 49.17378,
      "longitude": 16.57162,
      "validFrom": "2025-06-30T00:00:00+02:00",
      "validTo": "2026-05-20T23:59:59+02:00",
      "isValid": true,
      "publicTextHtml": "<p>Z důvodu stavebních prací bude <strong>od pondělí 30. června 2025 do ukončení prací</strong> (předpoklad 20. května 2026) omezen provoz v ulici Jihlavské mezi křižovatkami s ulicemi Netroufalky a Dlouhou.</p>\n\n<p> </p>\n\n<drupal-media data-align=\"left\" data-entity-type=\"media\" data-entity-uuid=\"9b0569c5-e863-4e24-8b14-d3779cdd192b\" data-view-mode=\"\"></drupal-media>\n\n<p><strong> Trolejbusová linka 25</strong> bude v provozu pouze v úseku <strong>Nemocnice Bohunice – Líšeň, Jírova</strong>.<br />\n• Pro jízdu v úseku <strong>Osová – Nemocnice Bohunice</strong> bude možné využít pravidelné autobusové a tramvajové linky.</p>\n\n<p> </p>\n\n<drupal-media data-align=\"left\" data-entity-type=\"media\" data-entity-uuid=\"b2d6d691-c35d-4b6e-be2d-98f2754298c0\" data-view-mode=\"\"></drupal-media>\n\n<p> Zastávka <strong>Stará nemocnice</strong> linek 40 a N90 ve směru z centra bude přeložena k provizornímu nástupišti ve středním dělícím pásu v úrovni běžné zastávky.</p>\n\n<p> </p>\n\n<drupal-media data-align=\"left\" data-entity-type=\"media\" data-entity-uuid=\"081d77d8-0e25-42e5-805f-a4a5b5daf1ca\" data-view-mode=\"\"></drupal-media>\n\n<p><em> Schéma dopravních opatření – <a href=\"https://dpmb.cz/sites/default/files/infotabule/info_v2506-044_web.pdf\" target=\"_blank\">ke stažení</a></em></p>\n\n<drupal-media data-align=\"left\" data-entity-type=\"media\" data-entity-uuid=\"081d77d8-0e25-42e5-805f-a4a5b5daf1ca\" data-view-mode=\"\"></drupal-media>\n\n<p><em> Jízdní řády dotčených linek budou k dispozici v sekci <a href=\"https://www.dpmb.cz/jizdni-rady-zastavek-linek\">Jízdní řády</a>.</em></p>\n",
      "privateTextHtml": null,
      "type": "V",
      "affectedLines": [
        "25",
        "40",
        "N90"
      ]
    },
    {
      "id": 6,
      "number": "2506 Moutnice, u fary",
      "title": "Moutnice, u fary - směr Nesvačilka",
      "latitude": 49.050604,
      "longitude": 16.738851,
      "validFrom": "2025-06-16T07:00:00+02:00",
      "validTo": "2026-04-30T23:59:00+02:00",
      "isValid": true,
      "publicTextHtml": "Zastávka Moutnice, u fary\u00A0je pro směr do Nesvačilky přesunuta cca 40 metrů vpřed k domu č. 246. ",
      "privateTextHtml": null,
      "type": "V",
      "affectedLines": [
        "612"
      ]
    },
    {
      "id": 5,
      "number": "2505 Pohořelice, náměstí",
      "title": "Pohořelice, náměstí - směr Brno",
      "latitude": 48.980847,
      "longitude": 16.522416,
      "validFrom": "2025-05-06T12:00:00+02:00",
      "validTo": "2026-10-31T23:59:00+01:00",
      "isValid": true,
      "publicTextHtml": "Zastávka Pohořelice, náměstí je pro linky<font color=\"#009240\"><strong> 104</strong></font>, <font color=\"#009240\"><strong> 105</strong></font> a <font color=\"#009240\"><strong>108</strong></font> směr Brno přesunuta o cca 10 metrů zpět. ",
      "privateTextHtml": null,
      "type": "V",
      "affectedLines": [
        "104",
        "105",
        "108"
      ]
    },
    {
      "id": 3,
      "number": "VP 2503-212",
      "title": "Tišnov, náměstí Míru",
      "latitude": 49.348891,
      "longitude": 16.422683,
      "validFrom": "2025-03-31T00:00:00+02:00",
      "validTo": "2026-11-30T23:59:00+01:00",
      "isValid": true,
      "publicTextHtml": "Linka<font color=\"#009240\"><strong> 332</strong></font>: Jede ve\u00A0směru z Tišnova\u00A0od žel. st. odklonem ulicí Dvořáčkovou na svou stálou zastávku Riegrova.\u00A0Ve směru do Tišnova\u00A0obslouží zast. Riegrova u dočasně zřízeného označníku v\u00A0ulici Černohorská (těsně před okružní křižovatkou) a pokračuje k\u00A0žel. st. odklonem ulicí Dvořákovou – U Humpolky - Nádražní. Vynechá tak zastávku náměstí.\u00A0Obslouží také zastávku Nádražní (u Penny marketu)..<br/><br/> Linka<font color=\"#009240\"><strong> 333</strong></font>:\u00A0Ve směru z\u00A0Tišnova\u00A0u rychlých spojů také odklon Dvořáčkovou, spoje vedené přes Riegrovu bez úprav bez vlivu na zastávky.\u00A0Ve směru do Tišnova\u00A0odklon ulicemi Riegrova – Dvořákova – U Humpolky – Nádražní. Namísto zastávky náměstí zastaví v\u00A0zastávce Riegrova u gymnázia. Obslouží také zastávku Nádražní (u Penny marketu). Vybrané školní spoje linek<font color=\"#009240\"><strong> 153</strong></font>, <font color=\"#009240\"><strong> 311</strong></font>, <font color=\"#009240\"><strong> 312</strong></font>, <font color=\"#009240\"><strong> 331</strong></font>, <font color=\"#009240\"><strong> 334</strong></font> a <font color=\"#009240\"><strong>336</strong></font>\u00A0vedené na zastávku Riegrova jedou od žel. st. odklonem ulicemi Janáčkova a Dvořáčkova. Obslouží zastávku Riegrova u gymnázia. ",
      "privateTextHtml": null,
      "type": "V",
      "affectedLines": [
        "153",
        "311",
        "312",
        "331",
        "332",
        "333",
        "334",
        "336"
      ]
    },
    {
      "id": 1,
      "number": "VP 2503-206",
      "title": "Dražovice",
      "latitude": 49.193386,
      "longitude": 16.944051,
      "validFrom": "2025-03-10T00:00:00+01:00",
      "validTo": "2026-08-31T23:59:00+02:00",
      "isValid": true,
      "publicTextHtml": "Linka<font color=\"#009240\"><strong> 602</strong></font>:\u00A0Spoje v Dražovicích jedou po odklonové trase. Zastávky Dražovice a Dražovice, na kopci jsou bez obsluhy, náhradou je zřízena zastávka Dražovice, škola u budovy místní ZŠ. V této zastávce není možná bezpečná manipulace s jízdními koly, na zastávce tedy nebude nástup a výstup s jízdním kolem možný. ",
      "privateTextHtml": null,
      "type": "V",
      "affectedLines": [
        "602"
      ]
    },
    {
      "id": 2,
      "number": "VP 2502-201",
      "title": "Jaroslavice, ul. Znojemská - havárie",
      "latitude": 48.757451,
      "longitude": 16.227649,
      "validFrom": "2025-02-17T00:00:00+01:00",
      "validTo": "2026-04-30T23:59:00+02:00",
      "isValid": true,
      "publicTextHtml": "Linka<font color=\"#009240\"><strong> 820</strong></font>\u00A0- veškeré spoje pojedou v úseku mezi zastávkami Slup resp. Slup, Oleksovičky, u mostu až Hrádek, kult. dům popřípadě až Jaroslavice odklonem po obousměrné objízdné trase po silnicích III/3978, III/40842, II/408 popřípadě i II/397 přes obce Strachotice a Valtrovice. Ve Hrádku budou zřízeny dočasné zastávky Hrádek, kult. dům také na silnici II/397\u00A0poblíž okružní křižovatky silnic II/408xII/397 přibližně před domem č.p. 32 pro linku<font color=\"#009240\"><strong> 820</strong></font> IDS JMK.",
      "privateTextHtml": null,
      "type": "V",
      "affectedLines": [
        "820",
        "821",
        "104"
      ]
    }
  ],
  "metadata": {
    "language": "cs",
    "fromCache": true,
    "warning": "Downloading data using automated tools is forbidden, for API access contact DPMB. Automatizované stahování dat není povolené, pro přístup k API kontaktujte DPMB.",
    "error": ""
  }
}